setup.py
gqrxHamlib/__init__.py
gqrxHamlib/gqrxHamlibGUI.py
gqrxHamlib.egg-info/PKG-INFO
gqrxHamlib.egg-info/SOURCES.txt
gqrxHamlib.egg-info/dependency_links.txt
gqrxHamlib.egg-info/entry_points.txt
gqrxHamlib.egg-info/top_level.txt