Metadata-Version: 1.0
Name: gqrxHamlib
Version: 3.2.2
Summary: gqrx-Hamlib interface
Home-page: http://github.com/g0fcu/gqrx-hamlib-gui
Author: Simon Kennedy
Author-email: UNKNOWN
License: GPL
Platform: UNKNOWN
